README.rst
setup.py
appy/__init__.py
appy/pod/__init__.py
appy/pod/actions.py
appy/pod/buffers.py
appy/pod/converter.py
appy/pod/doc_importers.py
appy/pod/elements.py
appy/pod/imageNotFound.jpg
appy/pod/odf_parser.py
appy/pod/parts.py
appy/pod/pod_parser.py
appy/pod/renderer.py
appy/pod/styles.in.content.xml
appy/pod/styles.in.styles.xml
appy/pod/styles_manager.py
appy/pod/xhtml2odt.py
appy/pod/test/Tester.py
appy/pod/test/__init__.py
appy/pod/test/contexts/Chart1.py
appy/pod/test/contexts/ColgroupTable.py
appy/pod/test/contexts/ElseStatements.py
appy/pod/test/contexts/Empty.py
appy/pod/test/contexts/FieldExpressions.py
appy/pod/test/contexts/FileHandlerImport.py
appy/pod/test/contexts/ForCell6.py
appy/pod/test/contexts/IfAndFors1.py
appy/pod/test/contexts/ImagesImport.py
appy/pod/test/contexts/OdsSimple.py
appy/pod/test/contexts/OnlyExpressions.py
appy/pod/test/contexts/PathImport.py
appy/pod/test/contexts/PersonsEight.py
appy/pod/test/contexts/PersonsFour.py
appy/pod/test/contexts/PersonsThree.py
appy/pod/test/contexts/PersonsTwo.py
appy/pod/test/contexts/SimpleForEmptyList.py
appy/pod/test/contexts/SimpleForFilledList.py
appy/pod/test/contexts/SimpleForRow.py
appy/pod/test/contexts/SimpleIfIsFalse.py
appy/pod/test/contexts/SimpleIfIsTrue.py
appy/pod/test/contexts/SimpleTest.py
appy/pod/test/contexts/VarStatements.py
appy/pod/test/contexts/XhtmlComplex.py
appy/pod/test/contexts/XhtmlComplex2.py
appy/pod/test/contexts/XhtmlComplex3.py
appy/pod/test/contexts/XhtmlComplex4.py
appy/pod/test/contexts/XhtmlComplex5.py
appy/pod/test/contexts/XhtmlComplex6.py
appy/pod/test/contexts/XhtmlComplex7.py
appy/pod/test/contexts/XhtmlComplex8.py
appy/pod/test/contexts/XhtmlComplexTables.py
appy/pod/test/contexts/XhtmlEntities.py
appy/pod/test/contexts/XhtmlKeepWithNext.py
appy/pod/test/contexts/XhtmlNominal.py
appy/pod/test/contexts/XhtmlStylesErrors.py
appy/pod/test/contexts/XhtmlStylesMapping.py
appy/pod/test/contexts/XhtmlTables.py
appy/pod/test/contexts/XhtmlWithStyle.py
appypod.egg-info/PKG-INFO
appypod.egg-info/SOURCES.txt
appypod.egg-info/dependency_links.txt
appypod.egg-info/top_level.txt