Metadata-Version: 1.1
Name: appypod
Version: 0.9.6
Summary: AppyPod
Home-page: https://github.com/stefanklug/appypod
Author: Gaëtan Delannay, modified by Stefan Klug
Author-email: klug.stefan@gmx.de
License: GPL
Keywords: odf template odf development
Platform: UNKNOWN
Classifier: Development Status :: 3 - Alpha
Classifier: Intended Audience :: Developers
Classifier: Topic :: Software Development :: Build Tools
Classifier: License :: OSI Approved :: MIT License
Classifier: Programming Language :: Python :: 3
Classifier: Programming Language :: Python :: 3.3
Classifier: Programming Language :: Python :: 3.4
